TrialPy/RCFA.py
TrialPy/_RCSingle.py
TrialPy/__init__.py
TrialPy/_arrangeCal.py
TrialPy/_forcesCal.py
TrialPy4-0.0.1.dist-info/LICENSE
TrialPy4-0.0.1.dist-info/METADATA
TrialPy4-0.0.1.dist-info/WHEEL
TrialPy4-0.0.1.dist-info/top_level.txt
TrialPy4-0.0.1.dist-info/RECORD
