Metadata-Version: 2.1
Name: TrialPy4
Version: 0.0.1
Summary: Object Oriented Structural Analysis
License: GNU LGPLv2.1
Classifier: Programming Language :: Python :: 3.10
Classifier: Operating System :: OS Independent
Requires-Python: >=3.10
License-File: LICENSE
Requires-Dist: numpy ==1.23.3
Requires-Dist: openpyxl ==3.0.10
Requires-Dist: pandas ==1.4.4
Requires-Dist: plotly ==5.10.0
Requires-Dist: ray ==2.6.1
